simplecalculate/__init__.py
simplecalculate-0.0.2.dist-info/METADATA
simplecalculate-0.0.2.dist-info/WHEEL
simplecalculate-0.0.2.dist-info/top_level.txt
simplecalculate-0.0.2.dist-info/RECORD
