Metadata-Version: 2.1
Name: simplecalculate
Version: 0.0.2
Summary: basic calculation
Home-page: UNKNOWN
Author: GiantCoder
Author-email: 
License: UNKNOWN
Platform: UNKNOWN
